{
  "id": "ac&us/dcu",
  "title": "M贸dulo 2: Dise帽o Web Centrado en el Usuario",
  "description": " Dise帽ar pensando en quienes realmente usan la web",
  "source": "@site/docs/ac&us/dcu.md",
  "sourceDirName": "ac&us",
  "slug": "/ac&us/dcu",
  "permalink": "/docuQuest/docs/ac&us/dcu",
  "draft": false,
  "unlisted": false,
  "editUrl": "https://github.com/OslarCode/OslarCode/docs/ac&us/dcu.md",
  "tags": [],
  "version": "current",
  "frontMatter": {},
  "sidebar": "tutorialSidebar",
  "previous": {
    "title": "M贸dulo 1: Introducci贸n a la Usabilidad Web",
    "permalink": "/docuQuest/docs/ac&us/introduccion"
  },
  "next": {
    "title": "M贸dulo 3: Dise帽o Conceptual y Prototipado",
    "permalink": "/docuQuest/docs/ac&us/dcp"
  }
}