{
  "id": "flex/沁ｯ align-self en Flexbox Alineacioﾌ］ individual en  5da8b1f7a9ef4c829ef9f1aa93c1efe7",
  "title": "沁ｯ align-self en Flexbox: Alineaciﾃｳn individual en el eje cruzado",
  "description": "沒 ﾂｿQuﾃｩ es align-self?",
  "source": "@site/docs/flex/沁ｯ align-self en Flexbox Alineacioﾌ］ individual en  5da8b1f7a9ef4c829ef9f1aa93c1efe7.md",
  "sourceDirName": "flex",
  "slug": "/flex/沁ｯ align-self en Flexbox Alineacioﾌ］ individual en  5da8b1f7a9ef4c829ef9f1aa93c1efe7",
  "permalink": "/docs/flex/沁ｯ align-self en Flexbox Alineacioﾌ］ individual en  5da8b1f7a9ef4c829ef9f1aa93c1efe7",
  "draft": false,
  "unlisted": false,
  "editUrl": "https://github.com/OslarCode/OslarCode/docs/flex/沁ｯ align-self en Flexbox Alineacioﾌ］ individual en  5da8b1f7a9ef4c829ef9f1aa93c1efe7.md",
  "tags": [],
  "version": "current",
  "frontMatter": {}
}