{
  "id": "js/variables",
  "title": "Variables",
  "description": "¿Qué son las Variables en JavaScript?",
  "source": "@site/docs/js/variables.md",
  "sourceDirName": "js",
  "slug": "/js/variables",
  "permalink": "/docuQuest/docs/js/variables",
  "draft": false,
  "unlisted": false,
  "editUrl": "https://github.com/OslarCode/OslarCode/docs/js/variables.md",
  "tags": [],
  "version": "current",
  "frontMatter": {},
  "sidebar": "tutorialSidebar",
  "previous": {
    "title": "Comentarios",
    "permalink": "/docuQuest/docs/js/comentarios"
  },
  "next": {
    "title": "Let",
    "permalink": "/docuQuest/docs/js/let"
  }
}